htty/__init__.py
htty/cli.py
htty/exceptions.py
htty/ht.py
htty/keys.py
htty/_bundled/ht
htty-0.1.18.dist-info/METADATA
htty-0.1.18.dist-info/WHEEL
htty-0.1.18.dist-info/entry_points.txt
htty-0.1.18.dist-info/RECORD
