Metadata-Version: 2.4
Name: htty
Version: 0.1.18
Summary: A python wrapper around ht (a headless terminal utility)
Project-URL: Homepage, https://github.com/MatrixManAtYrService/htty
Project-URL: Repository, https://github.com/MatrixManAtYrService/htty
Project-URL: Bug Tracker, https://github.com/MatrixManAtYrService/htty/issues
Author-email: Matt Rixman <MatrixManAtYrService@users.noreply.github.com>
License: MIT
Keywords: cli,emulator,terminal,testing
Classifier: Development Status :: 3 - Alpha
Classifier: Environment :: Console
Classifier: Intended Audience :: Developers
Classifier: License :: OSI Approved :: MIT License
Classifier: Operating System :: POSIX
Classifier: Programming Language :: Python :: 3
Classifier: Programming Language :: Python :: 3.10
Classifier: Programming Language :: Python :: 3.11
Classifier: Programming Language :: Python :: 3.12
Classifier: Topic :: Software Development :: Testing
Classifier: Topic :: Terminals :: Terminal Emulators/X Terminals
Requires-Python: >=3.10
Requires-Dist: ansi2html>=1.9.2
